enstaller4rc/__init__.py
enstaller4rc/_placeholders.py
enstaller4rc/_platform.py
enstaller4rc/config.py
enstaller4rc/errors.py
enstaller4rc/utils.py
enstaller4rc/tests/__init__.py
enstaller4rc/tests/test__placeholders.py
enstaller4rc/tests/test_config.py
enstaller4rc/tests/test_utils.py
enstaller4rc-0.0.1.dist-info/DESCRIPTION.rst
enstaller4rc-0.0.1.dist-info/METADATA
enstaller4rc-0.0.1.dist-info/RECORD
enstaller4rc-0.0.1.dist-info/WHEEL
enstaller4rc-0.0.1.dist-info/metadata.json
enstaller4rc-0.0.1.dist-info/top_level.txt
