Metadata-Version: 2.0
Name: enstaller4rc
Version: 0.0.1
Summary: .. image:: https://travis-ci.org/enthought/enstaller4rc.png
Requires-Dist: attrs (>=15.2.0)
Requires-Dist: six (>=1.10)
